{
  "main": {
    "id": "35fcc22d809c7a0d",
    "type": "split",
    "children": [
      {
        "id": "0e4c02596d041ba8",
        "type": "tabs",
        "children": [
          {
            "id": "e6967362678ecd74",
            "type": "leaf",
            "state": {
              "type": "markdown",
              "state": {
                "file": "Linux - Configurando DNS com BIND9.md",
                "mode": "source",
                "source": false
              }
            }
          }
        ]
      }
    ],
    "direction": "vertical"
  },
  "left": {
    "id": "b8f0746f07581905",
    "type": "split",
    "children": [
      {
        "id": "f3312851db2f188c",
        "type": "tabs",
        "children": [
          {
            "id": "29010bb3a568697f",
            "type": "leaf",
            "state": {
              "type": "file-explorer",
              "state": {
                "sortOrder": "alphabetical"
              }
            }
          },
          {
            "id": "5eea45199ee34543",
            "type": "leaf",
            "state": {
              "type": "search",
              "state": {
                "query": "PID",
                "matchingCase": false,
                "explainSearch": false,
                "collapseAll": false,
                "extraContext": false,
                "sortOrder": "alphabetical"
              }
            }
          },
          {
            "id": "ee73d2214f44081e",
            "type": "leaf",
            "state": {
              "type": "bookmarks",
              "state": {}
            }
          }
        ]
      }
    ],
    "direction": "horizontal",
    "width": 448.5,
    "collapsed": true
  },
  "right": {
    "id": "6e350f3182938e8a",
    "type": "split",
    "children": [
      {
        "id": "e0017cc517f779bf",
        "type": "tabs",
        "children": [
          {
            "id": "07a71ed64e0efe8a",
            "type": "leaf",
            "state": {
              "type": "backlink",
              "state": {
                "file": "Linux - Configurando DNS com BIND9.md",
                "collapseAll": false,
                "extraContext": false,
                "sortOrder": "alphabetical",
                "showSearch": false,
                "searchQuery": "",
                "backlinkCollapsed": false,
                "unlinkedCollapsed": true
              }
            }
          },
          {
            "id": "6c98c5032c3fdbd9",
            "type": "leaf",
            "state": {
              "type": "outgoing-link",
              "state": {
                "file": "Linux - Configurando DNS com BIND9.md",
                "linksCollapsed": false,
                "unlinkedCollapsed": true
              }
            }
          },
          {
            "id": "2d51d54584812601",
            "type": "leaf",
            "state": {
              "type": "tag",
              "state": {
                "sortOrder": "frequency",
                "useHierarchy": true
              }
            }
          },
          {
            "id": "d6abf66e7387819b",
            "type": "leaf",
            "state": {
              "type": "outline",
              "state": {
                "file": "Linux - Configurando DNS com BIND9.md"
              }
            }
          }
        ]
      }
    ],
    "direction": "horizontal",
    "width": 300,
    "collapsed": true
  },
  "left-ribbon": {
    "hiddenItems": {
      "switcher:Abrir a troca rápida": false,
      "graph:Abrir visualização em gráfico": false,
      "canvas:Criar novo canvas": false,
      "daily-notes:Abrir a nota de hoje": false,
      "templates:Inserir modelo": false,
      "command-palette:Abrir paleta de comandos": false,
      "obsidian-excalidraw-plugin:Create new drawing": false
    }
  },
  "active": "e6967362678ecd74",
  "lastOpenFiles": [
    "Linux - CentOS - BIND.md",
    "Linux - CentOS - BIND - Arquivo de zona de encaminhamento.md",
    "Linux - Configurando DNS com BIND9.md",
    "materias/Linux/Assuntos/Serviços.md",
    "Linux - CentOS - BIND - Arquivo local.md",
    "Linux - CentOS - BIND - Servidor DNS Primário.md",
    "Linux - CentOS - BIND - Inicial.md",
    "materias/Linux/Assuntos/Assuntos.md",
    "materias/cyber/Cyber - Assuntos.md",
    "Cyber - Reverse Shell.md",
    "cursos/HTB/HTB - Password Attacks/HTB - Password Attacks - Capítulos.md",
    "materias/cyber/Cyber - Técnicas.md",
    "Cyber - Busca de credenciais no Windows.md",
    "Pasted image 20240913194325.png",
    "Pasted image 20240913193732.png",
    "Cyber - Atacando o Active Directory e NTDS.dit.md",
    "Pasted image 20240913171101.png",
    "Pasted image 20240913171023.png",
    "Pasted image 20240913170643.png",
    "Pasted image 20240913170548.png",
    "Pasted image 20240913161752.png",
    "Pasted image 20240913161445.png",
    "Pasted image 20240913161350.png",
    "Pasted image 20240913160534.png",
    "cursos/RedHat/RedHat - System Administration 2/Redhat - System Administration 2 - Capítulos.md",
    "Linux - Gerenciamento do ciclo de vida de contêineres.md",
    "Linux -Criação de contêineres com o Podman.md",
    "Linux - Introdução aos contêineres.md",
    "Cyber - Reverse Shell na mão.md",
    "Linux - Gerenciamento de armazenamento em camadas.md",
    "Linux - Criação e extensão de volumes lógicos.md",
    "Cyber - Armazenamento de credenciais.md",
    "cursos/HackingClub/Hacking Club - Web Hacking na Prática.md",
    "Cyber - SQL Injection.md",
    "materias/cyber/Tips.md",
    "cursos/HTB/HTB - Coleta de informações - Edição Web/HTB - Coleta de informações - Edição Web - Capítulos.md",
    "cursos/Microsoft Learning/módulos",
    "Excalidraw",
    "cursos/HTB/HTB - Password Attacks",
    "cursos/NetAcad/NetAcad - C Essentials 1",
    "cursos/NetAcad",
    "cursos/RedHat/RedHat - System Administration 2",
    "cursos/HTB/HTB - Shells e Payloads",
    "materias/Linux/CentOS 9 Stream",
    "cursos/HTB/HTB - Transferência de arquivos",
    "materiais",
    "Untitled 2.canvas",
    "Untitled 1.canvas",
    "Untitled.canvas",
    "Sem título.canvas",
    "Sem título 1.canvas"
  ]
}