{
  "main": {
    "id": "35fcc22d809c7a0d",
    "type": "split",
    "children": [
      {
        "id": "5b624ba0d662eff5",
        "type": "tabs",
        "children": [
          {
            "id": "ad4b527b22dbd9eb",
            "type": "leaf",
            "state": {
              "type": "markdown",
              "state": {
                "file": "cursos/NetAcad/NetAcad - C Essentials 1/NetAcad - CE1 - Módulos.md",
                "mode": "source",
                "source": false
              }
            }
          },
          {
            "id": "8eeb59ed01ca7cf7",
            "type": "leaf",
            "state": {
              "type": "markdown",
              "state": {
                "file": "Programação - Introdução aos operadores.md",
                "mode": "source",
                "source": false
              }
            }
          }
        ],
        "currentTab": 1
      }
    ],
    "direction": "vertical"
  },
  "left": {
    "id": "b8f0746f07581905",
    "type": "split",
    "children": [
      {
        "id": "f3312851db2f188c",
        "type": "tabs",
        "children": [
          {
            "id": "29010bb3a568697f",
            "type": "leaf",
            "state": {
              "type": "file-explorer",
              "state": {
                "sortOrder": "alphabetical"
              }
            }
          },
          {
            "id": "5eea45199ee34543",
            "type": "leaf",
            "state": {
              "type": "search",
              "state": {
                "query": "",
                "matchingCase": false,
                "explainSearch": false,
                "collapseAll": false,
                "extraContext": false,
                "sortOrder": "alphabetical"
              }
            }
          },
          {
            "id": "ee73d2214f44081e",
            "type": "leaf",
            "state": {
              "type": "bookmarks",
              "state": {}
            }
          }
        ]
      }
    ],
    "direction": "horizontal",
    "width": 586.5,
    "collapsed": true
  },
  "right": {
    "id": "6e350f3182938e8a",
    "type": "split",
    "children": [
      {
        "id": "e0017cc517f779bf",
        "type": "tabs",
        "children": [
          {
            "id": "07a71ed64e0efe8a",
            "type": "leaf",
            "state": {
              "type": "backlink",
              "state": {
                "file": "Programação - Introdução aos operadores.md",
                "collapseAll": false,
                "extraContext": false,
                "sortOrder": "alphabetical",
                "showSearch": false,
                "searchQuery": "",
                "backlinkCollapsed": false,
                "unlinkedCollapsed": true
              }
            }
          },
          {
            "id": "6c98c5032c3fdbd9",
            "type": "leaf",
            "state": {
              "type": "outgoing-link",
              "state": {
                "file": "Programação - Introdução aos operadores.md",
                "linksCollapsed": false,
                "unlinkedCollapsed": true
              }
            }
          },
          {
            "id": "2d51d54584812601",
            "type": "leaf",
            "state": {
              "type": "tag",
              "state": {
                "sortOrder": "frequency",
                "useHierarchy": true
              }
            }
          },
          {
            "id": "d6abf66e7387819b",
            "type": "leaf",
            "state": {
              "type": "outline",
              "state": {
                "file": "Programação - Introdução aos operadores.md"
              }
            }
          }
        ]
      }
    ],
    "direction": "horizontal",
    "width": 300,
    "collapsed": true
  },
  "left-ribbon": {
    "hiddenItems": {
      "switcher:Open quick switcher": false,
      "graph:Open graph view": false,
      "canvas:Create new canvas": false,
      "daily-notes:Open today's daily note": false,
      "templates:Insert template": false,
      "command-palette:Open command palette": false
    }
  },
  "active": "8eeb59ed01ca7cf7",
  "lastOpenFiles": [
    "cursos/NetAcad/NetAcad - C Essentials 1/NetAcad - CE1 - Módulos.md",
    "Programação - Introdução aos operadores.md",
    "Programação - Compreendendo números de ponto flutuante.md",
    "C - Números de ponto flutuante na vida real e na linguagem C.md",
    "Pasted image 20240830190006.png",
    "Programação - Números de ponto flutuante.md",
    "Programação - Números através das lentes de um computador.md",
    "C - Palavras chaves.md",
    "Pasted image 20240830181806.png",
    "C - Valores de variáveis.md",
    "C - Declarações de variáveis.md",
    "C - Tipos de variáveis.md",
    "C - Nomes de variáveis.md",
    "cursos/RedHat/Cursos feitos.md",
    "Linux - Montagem automática do armazenamento NAS.md",
    "Pasted image 20240830175151.png",
    "Pasted image 20240830174957.png",
    "Pasted image 20240830174942.png",
    "Pasted image 20240830174401.png",
    "Pasted image 20240830174313.png",
    "Pasted image 20240830173343.png",
    "Pasted image 20240830173303.png",
    "Pasted image 20240830172856.png",
    "cursos/RedHat/RedHat - System Administration 2/Redhat - System Administration 2 - Capítulos.md",
    "Linux - Gerenciar armazenamento NAS com NFS.md",
    "Linux - Gerenciamento do espaço de swap.md",
    "Linux - Adição de partições, sistemas de arquivos e montagens persistentes.md",
    "Linux - Influência no agendamento de processos.md",
    "Linux - Ajuste dos perfis de ajuste.md",
    "cursos/HTB/HTB - Shells e Payloads/HTB - Shells e Payloads.md",
    "Cyber - PHP WebShell.md",
    "Cyber - Antak WebShell.md",
    "Cyber - Laudanum, uma Webshell para governar todos eles.md",
    "Cyber - Introdução aos Web Shells.md",
    "Cyber - Gerando Shells Interativos.md",
    "Cyber - Infiltrando Unix&Linux.md",
    "cursos/NetAcad/NetAcad - C Essentials 1",
    "cursos/NetAcad",
    "cursos/RedHat/RedHat - System Administration 2",
    "cursos/HTB/HTB - Shells e Payloads",
    "materias/Linux/CentOS 9 Stream",
    "cursos/HTB/HTB - Transferência de arquivos",
    "materiais",
    "materias/cyber/cves",
    "cursos/RedHat/Red Hat - Administração de sistemas Red Hat",
    "cursos/RedHat",
    "Untitled 2.canvas",
    "Untitled 1.canvas",
    "Untitled.canvas",
    "Sem título.canvas",
    "Sem título 1.canvas"
  ]
}